diomindmap/__init__.py
diomindmap/__main__.py
diomindmap/cli.py
diomindmap/mindmap.py
diomindmap/node.py
diomindmap-0.1.5.dist-info/METADATA
diomindmap-0.1.5.dist-info/WHEEL
diomindmap-0.1.5.dist-info/entry_points.txt
diomindmap-0.1.5.dist-info/RECORD
