Metadata-Version: 2.1
Name: diomindmap
Version: 0.1.5
Summary: Create Draw.io mind map diagrams with indented text files.
Home-page: https://github.com/AnrichVS/diomindmap
Author: Anrich van Schalkwyk
Author-email: anrichvs@gmail.com
Requires-Python: >=3.7,<4.0
Classifier: Programming Language :: Python :: 3
Classifier: Programming Language :: Python :: 3.7
Classifier: Programming Language :: Python :: 3.8
Classifier: Programming Language :: Python :: 3.9
Classifier: Programming Language :: Python :: 3.10
Classifier: Programming Language :: Python :: 3.11
Requires-Dist: N2G (==0.3.3)
Requires-Dist: python-igraph (==0.10.6)
Requires-Dist: typer (==0.9.0)
Project-URL: Repository, https://github.com/AnrichVS/diomindmap
